mimikit/__init__.py
mimikit/checkpoint.py
mimikit/config.py
mimikit/io_spec.py
mimikit/utils.py
mimikit/demos/__init__.py
mimikit/demos/checkpoint_k_bests.py
mimikit/demos/clusterizer_app.py
mimikit/demos/ensemble_generator.py
mimikit/demos/freqnet.py
mimikit/demos/generate_from_checkpoint.py
mimikit/demos/seq2seq.py
mimikit/demos/srnn.py
mimikit/extract/__init__.py
mimikit/extract/clusters.py
mimikit/extract/from_neighbors.py
mimikit/extract/samplify.py
mimikit/extract/segment.py
mimikit/features/__init__.py
mimikit/features/dataset.py
mimikit/features/extractor.py
mimikit/features/functionals.py
mimikit/features/item_spec.py
mimikit/loops/__init__.py
mimikit/loops/callbacks.py
mimikit/loops/generate.py
mimikit/loops/generate_chunks.py
mimikit/loops/logger.py
mimikit/loops/samplers.py
mimikit/loops/train_loops.py
mimikit/models/__init__.py
mimikit/models/ensemble_generator.py
mimikit/models/nnn.py
mimikit/modules/__init__.py
mimikit/modules/activations.py
mimikit/modules/io.py
mimikit/modules/loss_functions.py
mimikit/modules/misc.py
mimikit/modules/no_nan_hooks.py
mimikit/modules/resamplers.py
mimikit/modules/targets.py
mimikit/networks/__init__.py
mimikit/networks/arm.py
mimikit/networks/mlp.py
mimikit/networks/parametrized_gaussian.py
mimikit/networks/poconet.py
mimikit/networks/s2s_lstm.py
mimikit/networks/s2s_lstm_v2.py
mimikit/networks/sample_rnn_v2.py
mimikit/networks/tied_autoencoder.py
mimikit/networks/transformers.py
mimikit/networks/wave_gan.py
mimikit/networks/wavenet_v2.py
mimikit/ui/__init__.py
mimikit/ui/config_view.py
mimikit/ui/file_picker.py
mimikit/ui/style_sheet.py
mimikit/ui/widgets.py
mimikit/views/__init__.py
mimikit/views/clusterizer_app.py
mimikit/views/clusters.py
mimikit/views/dataset.py
mimikit/views/functionals.py
mimikit/views/io_spec.py
mimikit/views/sample_rnn.py
mimikit/views/train_arm.py
mimikit/views/wavenet.py
mimikit-0.4.3.dist-info/LICENSE
mimikit-0.4.3.dist-info/METADATA
mimikit-0.4.3.dist-info/WHEEL
mimikit-0.4.3.dist-info/entry_points.txt
mimikit-0.4.3.dist-info/top_level.txt
mimikit-0.4.3.dist-info/RECORD
